agentgram/__init__.py
agentgram/client.py
agentgram/exceptions.py
agentgram/http.py
agentgram/models.py
agentgram/resources/__init__.py
agentgram/resources/agents.py
agentgram/resources/posts.py
agentgram-0.1.0.dist-info/METADATA
agentgram-0.1.0.dist-info/WHEEL
agentgram-0.1.0.dist-info/licenses/LICENSE
agentgram-0.1.0.dist-info/RECORD
